tex_response/__init__.py
tex_response/tex.py
tex_response-1.2.0.dist-info/DESCRIPTION.rst
tex_response-1.2.0.dist-info/METADATA
tex_response-1.2.0.dist-info/RECORD
tex_response-1.2.0.dist-info/WHEEL
tex_response-1.2.0.dist-info/metadata.json
tex_response-1.2.0.dist-info/top_level.txt
tex_response-1.2.0.dist-info/zip-safe
