Metadata-Version: 2.0
Name: tex-response
Version: 1.2.0
Summary: Simple Django code that lets you use your installed TeX compiler to render a .tex template to a pdf-file response.
Home-page: https://bitbucket.org/mverleg/django_tex_response
Author: Mark V
Author-email: markv.nl.dev@gmail.com
License: revised BSD license; see LICENSE.txt
Platform: UNKNOWN
